{"authors.": {"authors": ["Eitan Isaacson", "Daiki Ueno", "Ben Konrath", "Dan Winship", "dmustieles", "Kjartan Maraas", "Nohemi Fernandez", "Jiro Matsuzawa", "Alejandro Pi\u00f1eiro Iglesias", "Andrej \u017dnidar\u0161i\u010d"], "commits": [196, 73, 48, 20, 19, 18, 14, 13, 12, 12], "id": [2428, 4263, 4792, 697, 18, 46, 4804, 38, 723, 625]}, "authors.last month": {"authors": ["Daiki Ueno", "Amanpreet Singh Alam"], "commits": [3, 1], "id": [4263, 26]}, "authors.last year": {"authors": ["Daiki Ueno", "Shankar Prasad", "Piotr Dr\u0105g", "Rajesh Ranjan", "Amanpreet Singh Alam", "Andika Triwidada", "Ani Peter", "Ankitkumar Patel", "Ask H. Larsen", "Aurimas \u010cernius"], "commits": [11, 4, 3, 2, 1, 1, 1, 1, 1, 1], "id": [4263, 98, 16, 161, 26, 55, 181, 259, 120, 48]}}