{"authors.": {"authors": ["Damien Sandras", "Julien Puydt", "ED", "Jan Schampera", "Christian Rose", "Matthias Schneider", "Miguel Rodr\u00edguez P\u00e9rez", "Snark", "Kilian Krause", "dmustieles"], "commits": [4411, 1889, 667, 306, 213, 201, 143, 138, 94, 84], "id": [9094, 9106, 7167, 9111, 6, 9112, 7728, 9115, 9103, 18]}, "authors.last month": {"authors": ["Damien Sandras", "Sweta Kothari", "Aurimas \u010cernius", "Krishnababu Krothapalli", "Rajesh Ranjan", "Saibal Ray", "Wolfgang St\u00f6ggl"], "commits": [30, 2, 1, 1, 1, 1, 1], "id": [9094, 919, 48, 798, 161, 947, 526]}, "authors.last year": {"authors": ["Damien Sandras", "Julien Puydt", "ED", "dmustieles", "Piotr Dr\u0105g", "Shantha kumar", "Marek \u010cernock\u00fd", "Shankar Prasad", "ManojKumar Giri", "ngoswami"], "commits": [246, 133, 46, 10, 10, 6, 5, 5, 4, 4], "id": [9094, 9106, 7167, 18, 16, 931, 24, 98, 247, 84]}}