{"senders.": {"id": [580, 578, 587, 588, 590, 21913, 591, 3423, 19839, 3445], "senders": ["Jody Goldberg", "Morten Welinder", "Andreas J. Guelzow", "Jean Brefort", "Andreas Guelzow", "cottrell@ricardo.ecn.wfu.edu", "Emmanuel Pacaud", "Adrian Custer", "cbill.lam@gmail.com", "Nick Lamb"], "sent": [1620, 581, 483, 463, 190, 150, 116, 111, 102, 89]}, "senders.last month": {"id": [588, 63675, 38513, 51042, 53206, 53954], "senders": ["Jean Brefort", "sylvie.guegueniat@me.com", "jmu@fermtech.techfak.uni-bielefeld.de", "news.ftr@free.fr", "parrenin@ujf-grenoble.fr", "pere@hola.fou.net"], "sent": [2, 2, 1, 1, 1, 1]}, "senders.last year": {"id": [588, 578, 70068, 57098, 590, 21655, 32486, 48219, 12161, 3423], "senders": ["Jean Brefort", "Morten Welinder", "_@thomaslevine.com", "rex@levee.wustl.edu", "Andreas Guelzow", "competition@gmx.us", "greigsteve@gmail.com", "michael.uplawski@uplawski.eu", "aanatoly@gmail.com", "Adrian Custer"], "sent": [26, 23, 9, 7, 5, 5, 5, 5, 4, 4]}}