{"senders.": {"id": [60008, 949, 58927, 2411, 53031, 22599, 654, 69759, 4670, 37380], "senders": ["scott@asofyet.org", "Torsten Sch\u00f6nfeld", "rwmcfa1@neces.com", "Kevin Ryde", "pagaltzis@gmx.de", "d.j.kasak.dk@gmail.com", "Emmanuele Bassi", "zentara1@sbcglobal.net", "Thierry Vignaud", "jeffrey.ratcliffe@gmail.com"], "sent": [2201, 1424, 705, 451, 341, 312, 307, 231, 194, 176]}, "senders.last month": {"id": [2414, 22599, 949, 15747, 654, 63770, 43065, 60008, 20], "senders": ["Brian Manning", "d.j.kasak.dk@gmail.com", "Torsten Sch\u00f6nfeld", "asb.cpan@gmail.com", "Emmanuele Bassi", "t.funk@web.de", "lbmlist@hethcote.com", "scott@asofyet.org", "Yuri Myasoedov"], "sent": [8, 8, 3, 2, 2, 2, 1, 1, 1]}, "senders.last year": {"id": [2414, 22599, 949, 654, 11907, 20995, 35709, 63770, 64302, 4670], "senders": ["Brian Manning", "d.j.kasak.dk@gmail.com", "Torsten Sch\u00f6nfeld", "Emmanuele Bassi", "825864@gmail.com", "chrjae@gmail.com", "it@sca-uk.com", "t.funk@web.de", "terencejferraro@gmail.com", "Thierry Vignaud"], "sent": [58, 36, 31, 15, 11, 11, 11, 10, 9, 7]}}