{"senders.": {"id": [52, 788, 596, 1202, 15, 16177, 6422, 13976, 7893, 46804], "senders": ["JP St. Pierre", "Florian M\u00fcllner", "Owen W. Taylor", "Milan Bouchet-Valat", "Giovanni Campagna", "awilliam@opengroupware.us", "Sriram Ramkrishna", "allan.registos@smpc.steniel.com.ph", "Adam Williamson", "mathematical.coffee@gmail.com"], "sent": [533, 491, 376, 211, 202, 193, 171, 165, 144, 140]}, "senders.last month": {"id": [], "senders": [], "sent": []}, "senders.last year": {"id": [], "senders": [], "sent": []}}