{"authors.": {"authors": ["ChipX86", "William Jon McCann", "Mike Hearn", "Matthias Clasen", "John (J5) Palmieri", "Javier Jard\u00f3n", "Bastien Nocera", "Martin Pitt", "Aur\u00e9lien G\u00e2teau", "Colin Walters"], "commits": [190, 90, 25, 16, 11, 10, 6, 5, 4, 4], "id": [2672, 28, 2673, 74, 2626, 462, 504, 2054, 2674, 299]}, "authors.last month": {"authors": [], "commits": [], "id": []}, "authors.last year": {"authors": ["Evan Nemerson", "Andre Klapper", "Olav Vitters", "Ryan Lortie"], "commits": [2, 1, 1, 1], "id": [333, 256, 132, 425]}}