{"authors.": {"authors": ["Bastien Nocera", "Philip Withnall", "Tim-Philipp M\u00fcller", "Kjartan Maraas", "Ronald Bultje", "Priit Laes", "Jorge Gonzalez Gonzalez", "Christian Persch", "Miloslav Trmac", "dmustieles"], "commits": [4595, 675, 164, 158, 153, 122, 110, 103, 97, 94], "id": [504, 467, 2112, 46, 1978, 87, 243, 407, 371, 18]}, "authors.last month": {"authors": ["Bastien Nocera", "Jens Georg", "Rajesh Ranjan", "Alexander Shopov", "Amanpreet Singh Alam", "Arash Mousavi", "ElleUca", "Kjartan Maraas", "Krishnababu Krothapalli", "Miroslav Nikoli\u0107"], "commits": [25, 2, 2, 1, 1, 1, 1, 1, 1, 1], "id": [504, 1000, 161, 170, 26, 91, 466, 46, 798, 23]}, "authors.last year": {"authors": ["Bastien Nocera", "dmustieles", "Yosef Or Boczko", "Piotr Dr\u0105g", "Andika Triwidada", "Francisco Di\u00e9guez", "GunChleoc", "Kjartan Maraas", "Marek \u010cernock\u00fd", "ngoswami"], "commits": [491, 17, 14, 10, 8, 7, 7, 7, 6, 6], "id": [504, 18, 97, 16, 55, 17, 103, 46, 24, 84]}}